desktop.ini
primelib/__init__.py
primelib/desktop.ini
primelib/prime_numbers.py
primelib_clement_bonnet-0.0.1.dist-info/LICENSE
primelib_clement_bonnet-0.0.1.dist-info/METADATA
primelib_clement_bonnet-0.0.1.dist-info/WHEEL
primelib_clement_bonnet-0.0.1.dist-info/top_level.txt
primelib_clement_bonnet-0.0.1.dist-info/RECORD
