Metadata-Version: 2.1
Name: primelib-clement-bonnet
Version: 0.0.1
Summary: A small package to work with prime numbers
Home-page: https://github.com/clement-bonnet/medium-first-package
Author: Clément Bonnet
Author-email: clement.bonnet16@gmail.com
Classifier: Programming Language :: Python :: 3
Classifier: License :: OSI Approved :: MIT License
Classifier: Operating System :: OS Independent
License-File: LICENSE
